a_cv_imwrite_imread_plus/README.MD
a_cv_imwrite_imread_plus/__init__.py
a_cv_imwrite_imread_plus/requirements.txt
a_cv_imwrite_imread_plus/thirdparty.json
a_cv_imwrite_imread_plus-0.13.dist-info/LICENSE.rst
a_cv_imwrite_imread_plus-0.13.dist-info/METADATA
a_cv_imwrite_imread_plus-0.13.dist-info/WHEEL
a_cv_imwrite_imread_plus-0.13.dist-info/top_level.txt
a_cv_imwrite_imread_plus-0.13.dist-info/RECORD
