Metadata-Version: 2.1
Name: a-cv-imwrite-imread-plus
Version: 0.13
Summary: Less trouble reading/writing images with OpenCV (from url/path/buffer/base64...)
Home-page: https://github.com/hansalemaos/a_cv_imwrite_imread_plus
Author: Johannes Fischer
Author-email: aulasparticularesdealemaosp@gmail.com
License: MIT
Keywords: opencv,cv2,numpy,cv
Classifier: Development Status :: 4 - Beta
Classifier: Programming Language :: Python :: 3 :: Only
Classifier: Programming Language :: Python :: 3.10
Classifier: Topic :: Software Development :: Libraries :: Python Modules
Classifier: Topic :: Utilities
License-File: LICENSE.rst
Requires-Dist: Pillow
Requires-Dist: numpy
Requires-Dist: opencv-python
Requires-Dist: requests
Requires-Dist: tolerant-isinstance
Requires-Dist: touchtouch
